ppvits/__init__.py
ppvits/predict.py
ppvits/trainer.py
ppvits/data_utils/__init__.py
ppvits/data_utils/collate_fn.py
ppvits/data_utils/mel_processing.py
ppvits/data_utils/reader.py
ppvits/data_utils/sampler.py
ppvits/models/__init__.py
ppvits/models/attentions.py
ppvits/models/commons.py
ppvits/models/losses.py
ppvits/models/models.py
ppvits/models/modules.py
ppvits/models/transforms.py
ppvits/text/__init__.py
ppvits/text/cantonese.py
ppvits/text/cleaners.py
ppvits/text/english.py
ppvits/text/japanese.py
ppvits/text/korean.py
ppvits/text/mandarin.py
ppvits/text/ngu_dialect.py
ppvits/text/shanghainese.py
ppvits/text/symbol.py
ppvits/text/chinese_dialect_lexicons/README.md
ppvits/text/chinese_dialect_lexicons/changzhou.json
ppvits/text/chinese_dialect_lexicons/changzhou.ocd2
ppvits/text/chinese_dialect_lexicons/changzhou_3.json
ppvits/text/chinese_dialect_lexicons/changzhou_3.ocd2
ppvits/text/chinese_dialect_lexicons/cixi_2.json
ppvits/text/chinese_dialect_lexicons/cixi_2.ocd2
ppvits/text/chinese_dialect_lexicons/fuyang_2.json
ppvits/text/chinese_dialect_lexicons/fuyang_2.ocd2
ppvits/text/chinese_dialect_lexicons/hangzhou_2.json
ppvits/text/chinese_dialect_lexicons/hangzhou_2.ocd2
ppvits/text/chinese_dialect_lexicons/jiading_2.json
ppvits/text/chinese_dialect_lexicons/jiading_2.ocd2
ppvits/text/chinese_dialect_lexicons/jiashan_2.json
ppvits/text/chinese_dialect_lexicons/jiashan_2.ocd2
ppvits/text/chinese_dialect_lexicons/jingjiang_2.json
ppvits/text/chinese_dialect_lexicons/jingjiang_2.ocd2
ppvits/text/chinese_dialect_lexicons/jyutjyu_2.json
ppvits/text/chinese_dialect_lexicons/jyutjyu_2.ocd2
ppvits/text/chinese_dialect_lexicons/linping_2.json
ppvits/text/chinese_dialect_lexicons/linping_2.ocd2
ppvits/text/chinese_dialect_lexicons/ningbo_2.json
ppvits/text/chinese_dialect_lexicons/ningbo_2.ocd2
ppvits/text/chinese_dialect_lexicons/pinghu_2.json
ppvits/text/chinese_dialect_lexicons/pinghu_2.ocd2
ppvits/text/chinese_dialect_lexicons/ruao_2.json
ppvits-0.0.1.dist-info/LICENSE
ppvits-0.0.1.dist-info/METADATA
ppvits-0.0.1.dist-info/WHEEL
ppvits-0.0.1.dist-info/top_level.txt
ppvits-0.0.1.dist-info/RECORD
